neoload/__init__.py
neoload/__main__.py
neoload/version.py
neoload/version_manager.py
neoload/commands/__init__.py
neoload/commands/config.py
neoload/commands/docker.py
neoload/commands/fastfail.py
neoload/commands/login.py
neoload/commands/logout.py
neoload/commands/logs.py
neoload/commands/logs_url.py
neoload/commands/project.py
neoload/commands/report.py
neoload/commands/run.py
neoload/commands/status.py
neoload/commands/stop.py
neoload/commands/test_results.py
neoload/commands/test_settings.py
neoload/commands/validate.py
neoload/commands/wait.py
neoload/commands/workspaces.py
neoload/commands/zones.py
neoload/neoload_cli_lib/__init__.py
neoload/neoload_cli_lib/bad_as_code_exception.py
neoload/neoload_cli_lib/cli_exception.py
neoload/neoload_cli_lib/config_global.py
neoload/neoload_cli_lib/displayer.py
neoload/neoload_cli_lib/docker_lib.py
neoload/neoload_cli_lib/filtering.py
neoload/neoload_cli_lib/hooks.py
neoload/neoload_cli_lib/logs_tools.py
neoload/neoload_cli_lib/logs_traduction_map.py
neoload/neoload_cli_lib/name_resolver.py
neoload/neoload_cli_lib/neoLoad_project.py
neoload/neoload_cli_lib/paths.py
neoload/neoload_cli_lib/rest_crud.py
neoload/neoload_cli_lib/running_tools.py
neoload/neoload_cli_lib/schema_validation.py
neoload/neoload_cli_lib/tools.py
neoload/neoload_cli_lib/user_data.py
neoload/resources/__init__.py
neoload/resources/jinja/__init__.py
neoload/resources/jinja/builtin_console_summary.j2
neoload/resources/jinja/builtin_transactions_csv.j2
neoload/resources/jinja/custom_transactions_export.j2
neoload/resources/jinja/sample-custom-report.html.j2
neoload/resources/jinja/sample-trends-report.html.j2
neoload/resources/jinja/common/common.js
neoload/resources/jinja/common/external_data.html.j2
neoload/resources/jinja/common/general_details.html.j2
neoload/resources/jinja/common/header.j2
neoload/resources/jinja/common/hits_per_second.html.j2
neoload/resources/jinja/common/running_vus.html.j2
neoload/resources/jinja/common/styles.css
neoload-1.3.17.dist-info/licenses/LICENSE
neoload-1.3.17.dist-info/METADATA
neoload-1.3.17.dist-info/WHEEL
neoload-1.3.17.dist-info/entry_points.txt
neoload-1.3.17.dist-info/top_level.txt
neoload-1.3.17.dist-info/RECORD
