Metadata-Version: 2.4
Name: neoload
Version: 1.3.17
Summary: A command-line native utility for launching and observing NeoLoad performance tests
Home-page: https://github.com/Neotys-Labs/neoload-cli
Author: Neotys
Author-email: 
License: Apache 2.0
License-File: LICENSE
Requires-Dist: click>=7
Requires-Dist: pyconfig
Requires-Dist: appdirs
Requires-Dist: requests>=2.25.1
Requires-Dist: jsonschema
Requires-Dist: PyYAML>=5
Requires-Dist: junit_xml
Requires-Dist: termcolor
Requires-Dist: coloredlogs
Requires-Dist: gitignorefile
Requires-Dist: jinja2
Requires-Dist: python-dateutil
Requires-Dist: tqdm
Requires-Dist: requests_toolbelt
Requires-Dist: urllib3>=1.26.5
Requires-Dist: docker
Requires-Dist: pyparsing
Requires-Dist: simplejson
Requires-Dist: colorama
Requires-Dist: importlib-resources
Dynamic: author
Dynamic: description
Dynamic: description-content-type
Dynamic: home-page
Dynamic: license
Dynamic: license-file
Dynamic: requires-dist
Dynamic: summary
